{
  "dataset_id": "eda6d5e4-b6ed-478e-a92b-71e0baab84b6",
  "title": "בתי הדין השרעיים - קאדים",
  "organization": "משרד המשפטים",
  "tags": [
    "בתי הדין השרעיים",
    "משרד המשפטים"
  ],
  "categories": [
    "justice"
  ],
  "keywords": [
    "השרעיים",
    "בתי",
    "משרד",
    "קאדים",
    "הדין",
    "המשפטים"
  ],
  "resources": [
    {
      "resource_id": "10ffbeeb-7496-49b9-b45b-38657b645cfd",
      "title": "קאדים",
      "format": "CSV",
      "fields": [
        {
          "name": "_id",
          "type": "int",
          "semantic": "id"
        },
        {
          "name": "קאדים",
          "type": "text",
          "semantic": null
        }
      ],
      "total_records": 25
    },
    {
      "resource_id": "b56f2174-cdf9-4a34-8d22-30e2aec7e6b3",
      "title": "הוראות לפתיחת קובץ מאגר באמצעות תוכנת excel",
      "format": "PDF",
      "fields": [],
      "note": "Non-datastore format"
    }
  ],
  "field_availability": {
    "has_phone": false,
    "has_address": false,
    "has_location": false,
    "has_email": false,
    "has_date": false
  }
}