{
  "dataset_id": "e1c3d05f-35af-4756-ac71-47af149b8292",
  "title": "דוח מסכם 2017 - דיווחי ביצוע על החלטות ממשלה",
  "organization": "משרד ראש הממשלה ",
  "tags": [
    "ביצוע",
    "בקרה",
    "דוח",
    "דיווח",
    "החלטות ממשלה",
    "ממשל",
    "ממשל וחברה",
    "מעקב",
    "משרד ראש הממשלה",
    "פיקוח",
    "תכנון",
    "תרבות ארגונית"
  ],
  "categories": [
    "finance",
    "culture"
  ],
  "keywords": [
    "החלטות",
    "דוח",
    "מעקב",
    "הממשלה",
    "ביצוע",
    "דיווח",
    "תכנון",
    "וחברה",
    "משרד",
    "פיקוח",
    "בקרה",
    "מסכם",
    "תרבות",
    "ארגונית",
    "ראש",
    "ממשלה",
    "דיווחי",
    "ממשל"
  ],
  "resources": [
    {
      "resource_id": "f8d22c3d-6d28-4166-aee4-3d023fa337f3",
      "title": "דוח מסכם 2017 - דיווחי ביצוע על החלטות ממשלה",
      "format": "XLSX",
      "fields": [],
      "error": "HTTP Error 404: Not Found"
    }
  ],
  "field_availability": {
    "has_phone": false,
    "has_address": false,
    "has_location": false,
    "has_email": false,
    "has_date": false
  }
}